autodiff_107/__init__.py
autodiff_107/diff.py
autodiff_107/math.py
autodiff_107/optim.py
autodiff_107/rootfind.py
autodiff_107/viz.py
autodiff_107-0.1.0.dist-info/LICENSE
autodiff_107-0.1.0.dist-info/METADATA
autodiff_107-0.1.0.dist-info/WHEEL
autodiff_107-0.1.0.dist-info/top_level.txt
autodiff_107-0.1.0.dist-info/RECORD
