Metadata-Version: 2.1
Name: autodiff-107
Version: 0.1.0
Summary: An automatic differentiation package built as the final project for CS107
Home-page: https://github.com/cs107-errajexi/autodiff_107
Author: Eryk Pecyna, Raphael Pellegrin, Jean-Guillaume Brasier, Xiyu Yang
Author-email: erykpecyna@college.harvard.edu
License: UNKNOWN
Platform: UNKNOWN
Classifier: Development Status :: 4 - Beta
Classifier: Intended Audience :: Education
Classifier: Intended Audience :: Science/Research
Classifier: License :: OSI Approved :: MIT License
Classifier: Programming Language :: Python :: 3
Requires-Python: >=3.6
License-File: LICENSE
Requires-Dist: numpy
Requires-Dist: matplotlib
Requires-Dist: networkx
